time_series_transformer/__init__.py
time_series_transformer/decoder.py
time_series_transformer/encoder.py
time_series_transformer/multi_head_attention.py
time_series_transformer/positionwise_feed_forward.py
time_series_transformer/transformer.py
time_series_transformer/utils.py
time_series_transformer-1.0.2.dist-info/LICENSE
time_series_transformer-1.0.2.dist-info/METADATA
time_series_transformer-1.0.2.dist-info/WHEEL
time_series_transformer-1.0.2.dist-info/top_level.txt
time_series_transformer-1.0.2.dist-info/RECORD
