Metadata-Version: 2.1
Name: time-series-transformer
Version: 1.0.2
Summary: Time Series Transformer
Home-page: https://github.com/DanielAtKrypton/time_series_transformer
Author: Daniel Kaminski de Souza
Author-email: daniel@kryptonunite.com
License: UNKNOWN
Platform: UNKNOWN
Classifier: Programming Language :: Python :: 3
Classifier: License :: OSI Approved :: GNU General Public License v3 (GPLv3)
Classifier: Operating System :: OS Independent
Requires-Python: >=3.6
Requires-Dist: torch
Provides-Extra: dev
Requires-Dist: autopep8 ; extra == 'dev'
Requires-Dist: bumpversion ; extra == 'dev'
Requires-Dist: pylint ; extra == 'dev'
Requires-Dist: twine ; extra == 'dev'
Provides-Extra: docs
Provides-Extra: test
Requires-Dist: flights-time-series-dataset ; extra == 'test'
Requires-Dist: pytest-cov ; extra == 'test'
Requires-Dist: pytest (>=4.6) ; extra == 'test'
Requires-Dist: time-series-predictor ; extra == 'test'
